[
  {
    "ContainingType": "Hoangnhhe171693.Controllers.CertificateController",
    "Method": "AddCertificateAsync",
    "RelativePath": "api/Certificate/add-certificate",
    "HttpMethod": "POST",
    "IsController": true,
    "Order": 0,
    "Parameters": [
      {
        "Name": "create",
        "Type": "Hoangnhhe171693.Models.DTO.Request.Certificate.CertificateCreate",
        "IsRequired": true
      }
    ],
    "ReturnTypes": [
      {
        "Type": "System.Collections.Generic.IEnumerable\u00601[[Hoangnhhe171693.Models.Certificate, Hoangnhhe171693, Version=1.0.0.0, Culture=neutral, PublicKeyToken=null]]",
        "MediaTypes": [
          "text/plain",
          "application/json",
          "text/json"
        ],
        "StatusCode": 200
      },
      {
        "Type": "System.String",
        "MediaTypes": [
          "text/plain",
          "application/json",
          "text/json"
        ],
        "StatusCode": 400
      }
    ]
  },
  {
    "ContainingType": "Hoangnhhe171693.Controllers.CertificateController",
    "Method": "SoftDeleteCertificateAsync",
    "RelativePath": "api/Certificate/change-status/{id}",
    "HttpMethod": "PUT",
    "IsController": true,
    "Order": 0,
    "Parameters": [
      {
        "Name": "id",
        "Type": "System.Int32",
        "IsRequired": true
      },
      {
        "Name": "newStatus",
        "Type": "System.String",
        "IsRequired": false
      }
    ],
    "ReturnTypes": [
      {
        "Type": "System.Collections.Generic.IEnumerable\u00601[[Hoangnhhe171693.Models.Certificate, Hoangnhhe171693, Version=1.0.0.0, Culture=neutral, PublicKeyToken=null]]",
        "MediaTypes": [
          "text/plain",
          "application/json",
          "text/json"
        ],
        "StatusCode": 200
      },
      {
        "Type": "System.String",
        "MediaTypes": [
          "text/plain",
          "application/json",
          "text/json"
        ],
        "StatusCode": 400
      }
    ]
  },
  {
    "ContainingType": "Hoangnhhe171693.Controllers.CertificateController",
    "Method": "HardDeleteCertificateAsync",
    "RelativePath": "api/Certificate/delete-permanent/{id}",
    "HttpMethod": "DELETE",
    "IsController": true,
    "Order": 0,
    "Parameters": [
      {
        "Name": "id",
        "Type": "System.Int32",
        "IsRequired": true
      }
    ],
    "ReturnTypes": [
      {
        "Type": "System.Collections.Generic.IEnumerable\u00601[[Hoangnhhe171693.Models.Certificate, Hoangnhhe171693, Version=1.0.0.0, Culture=neutral, PublicKeyToken=null]]",
        "MediaTypes": [
          "text/plain",
          "application/json",
          "text/json"
        ],
        "StatusCode": 200
      },
      {
        "Type": "System.String",
        "MediaTypes": [
          "text/plain",
          "application/json",
          "text/json"
        ],
        "StatusCode": 400
      }
    ]
  },
  {
    "ContainingType": "Hoangnhhe171693.Controllers.CertificateController",
    "Method": "FindByNameAsync",
    "RelativePath": "api/Certificate/find-by-name/{name}",
    "HttpMethod": "GET",
    "IsController": true,
    "Order": 0,
    "Parameters": [
      {
        "Name": "name",
        "Type": "System.String",
        "IsRequired": true
      }
    ],
    "ReturnTypes": [
      {
        "Type": "System.Collections.Generic.IEnumerable\u00601[[Hoangnhhe171693.Models.Certificate, Hoangnhhe171693, Version=1.0.0.0, Culture=neutral, PublicKeyToken=null]]",
        "MediaTypes": [
          "text/plain",
          "application/json",
          "text/json"
        ],
        "StatusCode": 200
      },
      {
        "Type": "System.String",
        "MediaTypes": [
          "text/plain",
          "application/json",
          "text/json"
        ],
        "StatusCode": 400
      }
    ]
  },
  {
    "ContainingType": "Hoangnhhe171693.Controllers.CertificateController",
    "Method": "FindByIdAsync",
    "RelativePath": "api/Certificate/find-Id/{id}",
    "HttpMethod": "GET",
    "IsController": true,
    "Order": 0,
    "Parameters": [
      {
        "Name": "id",
        "Type": "System.Int32",
        "IsRequired": true
      }
    ],
    "ReturnTypes": [
      {
        "Type": "System.Collections.Generic.IEnumerable\u00601[[Hoangnhhe171693.Models.Certificate, Hoangnhhe171693, Version=1.0.0.0, Culture=neutral, PublicKeyToken=null]]",
        "MediaTypes": [
          "text/plain",
          "application/json",
          "text/json"
        ],
        "StatusCode": 200
      },
      {
        "Type": "System.String",
        "MediaTypes": [
          "text/plain",
          "application/json",
          "text/json"
        ],
        "StatusCode": 400
      }
    ]
  },
  {
    "ContainingType": "Hoangnhhe171693.Controllers.CertificateController",
    "Method": "GetAllCertificateAsync",
    "RelativePath": "api/Certificate/get-all",
    "HttpMethod": "GET",
    "IsController": true,
    "Order": 0,
    "Parameters": [],
    "ReturnTypes": [
      {
        "Type": "System.Collections.Generic.IEnumerable\u00601[[Hoangnhhe171693.Models.Certificate, Hoangnhhe171693, Version=1.0.0.0, Culture=neutral, PublicKeyToken=null]]",
        "MediaTypes": [
          "text/plain",
          "application/json",
          "text/json"
        ],
        "StatusCode": 200
      },
      {
        "Type": "System.String",
        "MediaTypes": [
          "text/plain",
          "application/json",
          "text/json"
        ],
        "StatusCode": 400
      }
    ]
  },
  {
    "ContainingType": "Hoangnhhe171693.Controllers.CertificateController",
    "Method": "UpdateCertificateAsync",
    "RelativePath": "api/Certificate/update/{id}",
    "HttpMethod": "PUT",
    "IsController": true,
    "Order": 0,
    "Parameters": [
      {
        "Name": "update",
        "Type": "Hoangnhhe171693.Models.DTO.Request.Certificate.CertificateUpdate",
        "IsRequired": true
      },
      {
        "Name": "id",
        "Type": "System.Int32",
        "IsRequired": true
      }
    ],
    "ReturnTypes": [
      {
        "Type": "System.Collections.Generic.IEnumerable\u00601[[Hoangnhhe171693.Models.Certificate, Hoangnhhe171693, Version=1.0.0.0, Culture=neutral, PublicKeyToken=null]]",
        "MediaTypes": [
          "text/plain",
          "application/json",
          "text/json"
        ],
        "StatusCode": 200
      },
      {
        "Type": "System.String",
        "MediaTypes": [
          "text/plain",
          "application/json",
          "text/json"
        ],
        "StatusCode": 400
      }
    ]
  },
  {
    "ContainingType": "Hoangnhhe171693.Controllers.EmployeeController",
    "Method": "AddEmployeeAsync",
    "RelativePath": "api/Employee/add-employee",
    "HttpMethod": "POST",
    "IsController": true,
    "Order": 0,
    "Parameters": [
      {
        "Name": "create",
        "Type": "Hoangnhhe171693.Models.DTO.Request.Employee.EmployeeCreate",
        "IsRequired": true
      }
    ],
    "ReturnTypes": [
      {
        "Type": "System.Collections.Generic.IEnumerable\u00601[[Hoangnhhe171693.Models.Employee, Hoangnhhe171693, Version=1.0.0.0, Culture=neutral, PublicKeyToken=null]]",
        "MediaTypes": [
          "text/plain",
          "application/json",
          "text/json"
        ],
        "StatusCode": 200
      },
      {
        "Type": "System.String",
        "MediaTypes": [
          "text/plain",
          "application/json",
          "text/json"
        ],
        "StatusCode": 400
      }
    ]
  },
  {
    "ContainingType": "Hoangnhhe171693.Controllers.EmployeeController",
    "Method": "SoftDeleteEmployeeAsync",
    "RelativePath": "api/Employee/change-status/{id}",
    "HttpMethod": "PUT",
    "IsController": true,
    "Order": 0,
    "Parameters": [
      {
        "Name": "id",
        "Type": "System.Int32",
        "IsRequired": true
      },
      {
        "Name": "newStatus",
        "Type": "System.String",
        "IsRequired": false
      }
    ],
    "ReturnTypes": [
      {
        "Type": "System.Collections.Generic.IEnumerable\u00601[[Hoangnhhe171693.Models.Employee, Hoangnhhe171693, Version=1.0.0.0, Culture=neutral, PublicKeyToken=null]]",
        "MediaTypes": [
          "text/plain",
          "application/json",
          "text/json"
        ],
        "StatusCode": 200
      },
      {
        "Type": "System.String",
        "MediaTypes": [
          "text/plain",
          "application/json",
          "text/json"
        ],
        "StatusCode": 400
      }
    ]
  },
  {
    "ContainingType": "Hoangnhhe171693.Controllers.EmployeeController",
    "Method": "HardDeleteEmployeeAsync",
    "RelativePath": "api/Employee/delete-permanent/{id}",
    "HttpMethod": "DELETE",
    "IsController": true,
    "Order": 0,
    "Parameters": [
      {
        "Name": "id",
        "Type": "System.Int32",
        "IsRequired": true
      }
    ],
    "ReturnTypes": [
      {
        "Type": "System.Collections.Generic.IEnumerable\u00601[[Hoangnhhe171693.Models.Employee, Hoangnhhe171693, Version=1.0.0.0, Culture=neutral, PublicKeyToken=null]]",
        "MediaTypes": [
          "text/plain",
          "application/json",
          "text/json"
        ],
        "StatusCode": 200
      },
      {
        "Type": "System.String",
        "MediaTypes": [
          "text/plain",
          "application/json",
          "text/json"
        ],
        "StatusCode": 400
      }
    ]
  },
  {
    "ContainingType": "Hoangnhhe171693.Controllers.EmployeeController",
    "Method": "FindByNameAsync",
    "RelativePath": "api/Employee/find-by-name/{name}",
    "HttpMethod": "GET",
    "IsController": true,
    "Order": 0,
    "Parameters": [
      {
        "Name": "name",
        "Type": "System.String",
        "IsRequired": true
      }
    ],
    "ReturnTypes": [
      {
        "Type": "System.Collections.Generic.IEnumerable\u00601[[Hoangnhhe171693.Models.Employee, Hoangnhhe171693, Version=1.0.0.0, Culture=neutral, PublicKeyToken=null]]",
        "MediaTypes": [
          "text/plain",
          "application/json",
          "text/json"
        ],
        "StatusCode": 200
      },
      {
        "Type": "System.String",
        "MediaTypes": [
          "text/plain",
          "application/json",
          "text/json"
        ],
        "StatusCode": 400
      }
    ]
  },
  {
    "ContainingType": "Hoangnhhe171693.Controllers.EmployeeController",
    "Method": "FindByIdAsync",
    "RelativePath": "api/Employee/find-Id/{id}",
    "HttpMethod": "GET",
    "IsController": true,
    "Order": 0,
    "Parameters": [
      {
        "Name": "id",
        "Type": "System.Int32",
        "IsRequired": true
      }
    ],
    "ReturnTypes": [
      {
        "Type": "System.Collections.Generic.IEnumerable\u00601[[Hoangnhhe171693.Models.Employee, Hoangnhhe171693, Version=1.0.0.0, Culture=neutral, PublicKeyToken=null]]",
        "MediaTypes": [
          "text/plain",
          "application/json",
          "text/json"
        ],
        "StatusCode": 200
      },
      {
        "Type": "System.String",
        "MediaTypes": [
          "text/plain",
          "application/json",
          "text/json"
        ],
        "StatusCode": 400
      }
    ]
  },
  {
    "ContainingType": "Hoangnhhe171693.Controllers.EmployeeController",
    "Method": "GetAllEmployeeAsync",
    "RelativePath": "api/Employee/get-all",
    "HttpMethod": "GET",
    "IsController": true,
    "Order": 0,
    "Parameters": [],
    "ReturnTypes": [
      {
        "Type": "System.Collections.Generic.IEnumerable\u00601[[Hoangnhhe171693.Models.Employee, Hoangnhhe171693, Version=1.0.0.0, Culture=neutral, PublicKeyToken=null]]",
        "MediaTypes": [
          "text/plain",
          "application/json",
          "text/json"
        ],
        "StatusCode": 200
      },
      {
        "Type": "System.String",
        "MediaTypes": [
          "text/plain",
          "application/json",
          "text/json"
        ],
        "StatusCode": 400
      }
    ]
  },
  {
    "ContainingType": "Hoangnhhe171693.Controllers.EmployeeController",
    "Method": "UpdateEmployeeAsync",
    "RelativePath": "api/Employee/update/{id}",
    "HttpMethod": "PUT",
    "IsController": true,
    "Order": 0,
    "Parameters": [
      {
        "Name": "update",
        "Type": "Hoangnhhe171693.Models.DTO.Request.Employee.EmployeeUpdate",
        "IsRequired": true
      },
      {
        "Name": "id",
        "Type": "System.Int32",
        "IsRequired": true
      }
    ],
    "ReturnTypes": [
      {
        "Type": "System.Collections.Generic.IEnumerable\u00601[[Hoangnhhe171693.Models.Employee, Hoangnhhe171693, Version=1.0.0.0, Culture=neutral, PublicKeyToken=null]]",
        "MediaTypes": [
          "text/plain",
          "application/json",
          "text/json"
        ],
        "StatusCode": 200
      },
      {
        "Type": "System.String",
        "MediaTypes": [
          "text/plain",
          "application/json",
          "text/json"
        ],
        "StatusCode": 400
      }
    ]
  },
  {
    "ContainingType": "Hoangnhhe171693.Controllers.EmployeeCertificateController",
    "Method": "AddEmployeeCertificateAsync",
    "RelativePath": "api/EmployeeCertificate/add-empcer",
    "HttpMethod": "POST",
    "IsController": true,
    "Order": 0,
    "Parameters": [
      {
        "Name": "create",
        "Type": "Hoangnhhe171693.Models.DTO.Request.EmployeeCertificate.EmployeeCertificateCreate",
        "IsRequired": true
      }
    ],
    "ReturnTypes": [
      {
        "Type": "System.Collections.Generic.IEnumerable\u00601[[Hoangnhhe171693.Models.EmployeeCertificate, Hoangnhhe171693, Version=1.0.0.0, Culture=neutral, PublicKeyToken=null]]",
        "MediaTypes": [
          "text/plain",
          "application/json",
          "text/json"
        ],
        "StatusCode": 200
      },
      {
        "Type": "System.String",
        "MediaTypes": [
          "text/plain",
          "application/json",
          "text/json"
        ],
        "StatusCode": 400
      }
    ]
  },
  {
    "ContainingType": "Hoangnhhe171693.Controllers.EmployeeCertificateController",
    "Method": "HardDeleteEmployeeCertificateAsync",
    "RelativePath": "api/EmployeeCertificate/delete-permanent/{id}",
    "HttpMethod": "DELETE",
    "IsController": true,
    "Order": 0,
    "Parameters": [
      {
        "Name": "id",
        "Type": "System.Int32",
        "IsRequired": true
      }
    ],
    "ReturnTypes": [
      {
        "Type": "System.Collections.Generic.IEnumerable\u00601[[Hoangnhhe171693.Models.EmployeeCertificate, Hoangnhhe171693, Version=1.0.0.0, Culture=neutral, PublicKeyToken=null]]",
        "MediaTypes": [
          "text/plain",
          "application/json",
          "text/json"
        ],
        "StatusCode": 200
      },
      {
        "Type": "System.String",
        "MediaTypes": [
          "text/plain",
          "application/json",
          "text/json"
        ],
        "StatusCode": 400
      }
    ]
  },
  {
    "ContainingType": "Hoangnhhe171693.Controllers.EmployeeCertificateController",
    "Method": "FindByIdAsync",
    "RelativePath": "api/EmployeeCertificate/find-Id/{id}",
    "HttpMethod": "GET",
    "IsController": true,
    "Order": 0,
    "Parameters": [
      {
        "Name": "id",
        "Type": "System.Int32",
        "IsRequired": true
      }
    ],
    "ReturnTypes": [
      {
        "Type": "System.Collections.Generic.IEnumerable\u00601[[Hoangnhhe171693.Models.EmployeeCertificate, Hoangnhhe171693, Version=1.0.0.0, Culture=neutral, PublicKeyToken=null]]",
        "MediaTypes": [
          "text/plain",
          "application/json",
          "text/json"
        ],
        "StatusCode": 200
      },
      {
        "Type": "System.String",
        "MediaTypes": [
          "text/plain",
          "application/json",
          "text/json"
        ],
        "StatusCode": 400
      }
    ]
  },
  {
    "ContainingType": "Hoangnhhe171693.Controllers.EmployeeCertificateController",
    "Method": "GetAllEmployeeCertificateAsync",
    "RelativePath": "api/EmployeeCertificate/get-all",
    "HttpMethod": "GET",
    "IsController": true,
    "Order": 0,
    "Parameters": [],
    "ReturnTypes": [
      {
        "Type": "System.Collections.Generic.IEnumerable\u00601[[Hoangnhhe171693.Models.EmployeeCertificate, Hoangnhhe171693, Version=1.0.0.0, Culture=neutral, PublicKeyToken=null]]",
        "MediaTypes": [
          "text/plain",
          "application/json",
          "text/json"
        ],
        "StatusCode": 200
      },
      {
        "Type": "System.String",
        "MediaTypes": [
          "text/plain",
          "application/json",
          "text/json"
        ],
        "StatusCode": 400
      }
    ]
  },
  {
    "ContainingType": "Hoangnhhe171693.Controllers.EmployeeCertificateController",
    "Method": "GetActiveCertificatesByEmployeeIdAsync",
    "RelativePath": "api/EmployeeCertificate/get-certificate-by-employeeId",
    "HttpMethod": "GET",
    "IsController": true,
    "Order": 0,
    "Parameters": [
      {
        "Name": "id",
        "Type": "System.Int32",
        "IsRequired": false
      }
    ],
    "ReturnTypes": [
      {
        "Type": "System.Collections.Generic.IEnumerable\u00601[[Hoangnhhe171693.Models.EmployeeCertificate, Hoangnhhe171693, Version=1.0.0.0, Culture=neutral, PublicKeyToken=null]]",
        "MediaTypes": [
          "text/plain",
          "application/json",
          "text/json"
        ],
        "StatusCode": 200
      },
      {
        "Type": "System.String",
        "MediaTypes": [
          "text/plain",
          "application/json",
          "text/json"
        ],
        "StatusCode": 400
      }
    ]
  },
  {
    "ContainingType": "Hoangnhhe171693.Controllers.EmployeeCertificateController",
    "Method": "UpdateEmployeeCertificateAsync",
    "RelativePath": "api/EmployeeCertificate/update/{id}",
    "HttpMethod": "PUT",
    "IsController": true,
    "Order": 0,
    "Parameters": [
      {
        "Name": "update",
        "Type": "Hoangnhhe171693.Models.DTO.Request.EmployeeCertificate.EmployeeCertificateUpdate",
        "IsRequired": true
      },
      {
        "Name": "id",
        "Type": "System.Int32",
        "IsRequired": true
      }
    ],
    "ReturnTypes": [
      {
        "Type": "System.Collections.Generic.IEnumerable\u00601[[Hoangnhhe171693.Models.EmployeeCertificate, Hoangnhhe171693, Version=1.0.0.0, Culture=neutral, PublicKeyToken=null]]",
        "MediaTypes": [
          "text/plain",
          "application/json",
          "text/json"
        ],
        "StatusCode": 200
      },
      {
        "Type": "System.String",
        "MediaTypes": [
          "text/plain",
          "application/json",
          "text/json"
        ],
        "StatusCode": 400
      }
    ]
  },
  {
    "ContainingType": "Hoangnhhe171693.Controllers.HuyenController",
    "Method": "AddHuyenAsync",
    "RelativePath": "api/Huyen/add-huyen",
    "HttpMethod": "POST",
    "IsController": true,
    "Order": 0,
    "Parameters": [
      {
        "Name": "create",
        "Type": "Hoangnhhe171693.Models.DTO.Request.Huyen.HuyenCreate",
        "IsRequired": true
      }
    ],
    "ReturnTypes": [
      {
        "Type": "System.Collections.Generic.IEnumerable\u00601[[Hoangnhhe171693.Models.Huyen, Hoangnhhe171693, Version=1.0.0.0, Culture=neutral, PublicKeyToken=null]]",
        "MediaTypes": [
          "text/plain",
          "application/json",
          "text/json"
        ],
        "StatusCode": 200
      },
      {
        "Type": "System.String",
        "MediaTypes": [
          "text/plain",
          "application/json",
          "text/json"
        ],
        "StatusCode": 400
      }
    ]
  },
  {
    "ContainingType": "Hoangnhhe171693.Controllers.HuyenController",
    "Method": "SoftDeleteHuyenAsync",
    "RelativePath": "api/Huyen/change-status/{id}",
    "HttpMethod": "PUT",
    "IsController": true,
    "Order": 0,
    "Parameters": [
      {
        "Name": "id",
        "Type": "System.Int32",
        "IsRequired": true
      },
      {
        "Name": "newStatus",
        "Type": "System.String",
        "IsRequired": false
      }
    ],
    "ReturnTypes": [
      {
        "Type": "System.Collections.Generic.IEnumerable\u00601[[Hoangnhhe171693.Models.Huyen, Hoangnhhe171693, Version=1.0.0.0, Culture=neutral, PublicKeyToken=null]]",
        "MediaTypes": [
          "text/plain",
          "application/json",
          "text/json"
        ],
        "StatusCode": 200
      },
      {
        "Type": "System.String",
        "MediaTypes": [
          "text/plain",
          "application/json",
          "text/json"
        ],
        "StatusCode": 400
      }
    ]
  },
  {
    "ContainingType": "Hoangnhhe171693.Controllers.HuyenController",
    "Method": "HardDeleteHuyenAsync",
    "RelativePath": "api/Huyen/delete-permanent/{id}",
    "HttpMethod": "DELETE",
    "IsController": true,
    "Order": 0,
    "Parameters": [
      {
        "Name": "id",
        "Type": "System.Int32",
        "IsRequired": true
      }
    ],
    "ReturnTypes": [
      {
        "Type": "System.Collections.Generic.IEnumerable\u00601[[Hoangnhhe171693.Models.Huyen, Hoangnhhe171693, Version=1.0.0.0, Culture=neutral, PublicKeyToken=null]]",
        "MediaTypes": [
          "text/plain",
          "application/json",
          "text/json"
        ],
        "StatusCode": 200
      },
      {
        "Type": "System.String",
        "MediaTypes": [
          "text/plain",
          "application/json",
          "text/json"
        ],
        "StatusCode": 400
      }
    ]
  },
  {
    "ContainingType": "Hoangnhhe171693.Controllers.HuyenController",
    "Method": "FindByNameAsync",
    "RelativePath": "api/Huyen/find-by-name/{name}",
    "HttpMethod": "GET",
    "IsController": true,
    "Order": 0,
    "Parameters": [
      {
        "Name": "name",
        "Type": "System.String",
        "IsRequired": true
      }
    ],
    "ReturnTypes": [
      {
        "Type": "System.Collections.Generic.IEnumerable\u00601[[Hoangnhhe171693.Models.Huyen, Hoangnhhe171693, Version=1.0.0.0, Culture=neutral, PublicKeyToken=null]]",
        "MediaTypes": [
          "text/plain",
          "application/json",
          "text/json"
        ],
        "StatusCode": 200
      },
      {
        "Type": "System.String",
        "MediaTypes": [
          "text/plain",
          "application/json",
          "text/json"
        ],
        "StatusCode": 400
      }
    ]
  },
  {
    "ContainingType": "Hoangnhhe171693.Controllers.HuyenController",
    "Method": "FindByIdAsync",
    "RelativePath": "api/Huyen/find-Id/{postalCode}",
    "HttpMethod": "GET",
    "IsController": true,
    "Order": 0,
    "Parameters": [
      {
        "Name": "postalCode",
        "Type": "System.Int32",
        "IsRequired": true
      }
    ],
    "ReturnTypes": [
      {
        "Type": "System.Collections.Generic.IEnumerable\u00601[[Hoangnhhe171693.Models.Huyen, Hoangnhhe171693, Version=1.0.0.0, Culture=neutral, PublicKeyToken=null]]",
        "MediaTypes": [
          "text/plain",
          "application/json",
          "text/json"
        ],
        "StatusCode": 200
      },
      {
        "Type": "System.String",
        "MediaTypes": [
          "text/plain",
          "application/json",
          "text/json"
        ],
        "StatusCode": 400
      }
    ]
  },
  {
    "ContainingType": "Hoangnhhe171693.Controllers.HuyenController",
    "Method": "GetAllHuyenAsync",
    "RelativePath": "api/Huyen/get-all",
    "HttpMethod": "GET",
    "IsController": true,
    "Order": 0,
    "Parameters": [],
    "ReturnTypes": [
      {
        "Type": "System.Collections.Generic.IEnumerable\u00601[[Hoangnhhe171693.Models.Huyen, Hoangnhhe171693, Version=1.0.0.0, Culture=neutral, PublicKeyToken=null]]",
        "MediaTypes": [
          "text/plain",
          "application/json",
          "text/json"
        ],
        "StatusCode": 200
      },
      {
        "Type": "System.String",
        "MediaTypes": [
          "text/plain",
          "application/json",
          "text/json"
        ],
        "StatusCode": 400
      }
    ]
  },
  {
    "ContainingType": "Hoangnhhe171693.Controllers.HuyenController",
    "Method": "getHuyensByIdTinh",
    "RelativePath": "api/Huyen/tinh/{id}",
    "HttpMethod": "GET",
    "IsController": true,
    "Order": 0,
    "Parameters": [
      {
        "Name": "id",
        "Type": "System.Int32",
        "IsRequired": true
      }
    ],
    "ReturnTypes": [
      {
        "Type": "System.Collections.Generic.IEnumerable\u00601[[Hoangnhhe171693.Models.Huyen, Hoangnhhe171693, Version=1.0.0.0, Culture=neutral, PublicKeyToken=null]]",
        "MediaTypes": [
          "text/plain",
          "application/json",
          "text/json"
        ],
        "StatusCode": 200
      },
      {
        "Type": "System.String",
        "MediaTypes": [
          "text/plain",
          "application/json",
          "text/json"
        ],
        "StatusCode": 400
      }
    ]
  },
  {
    "ContainingType": "Hoangnhhe171693.Controllers.HuyenController",
    "Method": "UpdateHuyenAsync",
    "RelativePath": "api/Huyen/update/{id}",
    "HttpMethod": "PUT",
    "IsController": true,
    "Order": 0,
    "Parameters": [
      {
        "Name": "update",
        "Type": "Hoangnhhe171693.Models.DTO.Request.Huyen.HuyenUpdate",
        "IsRequired": true
      },
      {
        "Name": "id",
        "Type": "System.Int32",
        "IsRequired": true
      }
    ],
    "ReturnTypes": [
      {
        "Type": "System.Collections.Generic.IEnumerable\u00601[[Hoangnhhe171693.Models.Huyen, Hoangnhhe171693, Version=1.0.0.0, Culture=neutral, PublicKeyToken=null]]",
        "MediaTypes": [
          "text/plain",
          "application/json",
          "text/json"
        ],
        "StatusCode": 200
      },
      {
        "Type": "System.String",
        "MediaTypes": [
          "text/plain",
          "application/json",
          "text/json"
        ],
        "StatusCode": 400
      }
    ]
  },
  {
    "ContainingType": "Hoangnhhe171693.Controllers.TinhController",
    "Method": "AddTinhAsync",
    "RelativePath": "api/Tinh/add-tinh",
    "HttpMethod": "POST",
    "IsController": true,
    "Order": 0,
    "Parameters": [
      {
        "Name": "create",
        "Type": "Hoangnhhe171693.Models.DTO.Request.Tinh.TinhCreate",
        "IsRequired": true
      }
    ],
    "ReturnTypes": [
      {
        "Type": "System.Collections.Generic.IEnumerable\u00601[[Hoangnhhe171693.Models.Tinh, Hoangnhhe171693, Version=1.0.0.0, Culture=neutral, PublicKeyToken=null]]",
        "MediaTypes": [
          "text/plain",
          "application/json",
          "text/json"
        ],
        "StatusCode": 200
      },
      {
        "Type": "System.String",
        "MediaTypes": [
          "text/plain",
          "application/json",
          "text/json"
        ],
        "StatusCode": 400
      }
    ]
  },
  {
    "ContainingType": "Hoangnhhe171693.Controllers.TinhController",
    "Method": "SoftDeleteTinhAsync",
    "RelativePath": "api/Tinh/change-status/{id}",
    "HttpMethod": "PUT",
    "IsController": true,
    "Order": 0,
    "Parameters": [
      {
        "Name": "id",
        "Type": "System.Int32",
        "IsRequired": true
      },
      {
        "Name": "newStatus",
        "Type": "System.String",
        "IsRequired": false
      }
    ],
    "ReturnTypes": [
      {
        "Type": "System.Collections.Generic.IEnumerable\u00601[[Hoangnhhe171693.Models.Tinh, Hoangnhhe171693, Version=1.0.0.0, Culture=neutral, PublicKeyToken=null]]",
        "MediaTypes": [
          "text/plain",
          "application/json",
          "text/json"
        ],
        "StatusCode": 200
      },
      {
        "Type": "System.String",
        "MediaTypes": [
          "text/plain",
          "application/json",
          "text/json"
        ],
        "StatusCode": 400
      }
    ]
  },
  {
    "ContainingType": "Hoangnhhe171693.Controllers.TinhController",
    "Method": "HardDeleteTinhAsync",
    "RelativePath": "api/Tinh/delete-permanent/{id}",
    "HttpMethod": "DELETE",
    "IsController": true,
    "Order": 0,
    "Parameters": [
      {
        "Name": "id",
        "Type": "System.Int32",
        "IsRequired": true
      }
    ],
    "ReturnTypes": [
      {
        "Type": "System.Collections.Generic.IEnumerable\u00601[[Hoangnhhe171693.Models.Tinh, Hoangnhhe171693, Version=1.0.0.0, Culture=neutral, PublicKeyToken=null]]",
        "MediaTypes": [
          "text/plain",
          "application/json",
          "text/json"
        ],
        "StatusCode": 200
      },
      {
        "Type": "System.String",
        "MediaTypes": [
          "text/plain",
          "application/json",
          "text/json"
        ],
        "StatusCode": 400
      }
    ]
  },
  {
    "ContainingType": "Hoangnhhe171693.Controllers.TinhController",
    "Method": "FindByNameAsync",
    "RelativePath": "api/Tinh/find-by-name/{name}",
    "HttpMethod": "GET",
    "IsController": true,
    "Order": 0,
    "Parameters": [
      {
        "Name": "name",
        "Type": "System.String",
        "IsRequired": true
      }
    ],
    "ReturnTypes": [
      {
        "Type": "System.Collections.Generic.IEnumerable\u00601[[Hoangnhhe171693.Models.Tinh, Hoangnhhe171693, Version=1.0.0.0, Culture=neutral, PublicKeyToken=null]]",
        "MediaTypes": [
          "text/plain",
          "application/json",
          "text/json"
        ],
        "StatusCode": 200
      },
      {
        "Type": "System.String",
        "MediaTypes": [
          "text/plain",
          "application/json",
          "text/json"
        ],
        "StatusCode": 400
      }
    ]
  },
  {
    "ContainingType": "Hoangnhhe171693.Controllers.TinhController",
    "Method": "FindByIdAsync",
    "RelativePath": "api/Tinh/find-Id/{postalCode}",
    "HttpMethod": "GET",
    "IsController": true,
    "Order": 0,
    "Parameters": [
      {
        "Name": "postalCode",
        "Type": "System.Int32",
        "IsRequired": true
      }
    ],
    "ReturnTypes": [
      {
        "Type": "System.Collections.Generic.IEnumerable\u00601[[Hoangnhhe171693.Models.Tinh, Hoangnhhe171693, Version=1.0.0.0, Culture=neutral, PublicKeyToken=null]]",
        "MediaTypes": [
          "text/plain",
          "application/json",
          "text/json"
        ],
        "StatusCode": 200
      },
      {
        "Type": "System.String",
        "MediaTypes": [
          "text/plain",
          "application/json",
          "text/json"
        ],
        "StatusCode": 400
      }
    ]
  },
  {
    "ContainingType": "Hoangnhhe171693.Controllers.TinhController",
    "Method": "GetAllTinhAsync",
    "RelativePath": "api/Tinh/get-all",
    "HttpMethod": "GET",
    "IsController": true,
    "Order": 0,
    "Parameters": [],
    "ReturnTypes": [
      {
        "Type": "System.Collections.Generic.IEnumerable\u00601[[Hoangnhhe171693.Models.Tinh, Hoangnhhe171693, Version=1.0.0.0, Culture=neutral, PublicKeyToken=null]]",
        "MediaTypes": [
          "text/plain",
          "application/json",
          "text/json"
        ],
        "StatusCode": 200
      },
      {
        "Type": "System.String",
        "MediaTypes": [
          "text/plain",
          "application/json",
          "text/json"
        ],
        "StatusCode": 400
      }
    ]
  },
  {
    "ContainingType": "Hoangnhhe171693.Controllers.TinhController",
    "Method": "UpdateTinhAsync",
    "RelativePath": "api/Tinh/update/{id}",
    "HttpMethod": "PUT",
    "IsController": true,
    "Order": 0,
    "Parameters": [
      {
        "Name": "update",
        "Type": "Hoangnhhe171693.Models.DTO.Request.Tinh.TinhUpdate",
        "IsRequired": true
      },
      {
        "Name": "id",
        "Type": "System.Int32",
        "IsRequired": true
      }
    ],
    "ReturnTypes": [
      {
        "Type": "System.Collections.Generic.IEnumerable\u00601[[Hoangnhhe171693.Models.Tinh, Hoangnhhe171693, Version=1.0.0.0, Culture=neutral, PublicKeyToken=null]]",
        "MediaTypes": [
          "text/plain",
          "application/json",
          "text/json"
        ],
        "StatusCode": 200
      },
      {
        "Type": "System.String",
        "MediaTypes": [
          "text/plain",
          "application/json",
          "text/json"
        ],
        "StatusCode": 400
      }
    ]
  },
  {
    "ContainingType": "Hoangnhhe171693.Controllers.XaController",
    "Method": "AddXaAsync",
    "RelativePath": "api/Xa/add-xa",
    "HttpMethod": "POST",
    "IsController": true,
    "Order": 0,
    "Parameters": [
      {
        "Name": "create",
        "Type": "Hoangnhhe171693.Models.DTO.Request.Xa.XaCreate",
        "IsRequired": true
      }
    ],
    "ReturnTypes": [
      {
        "Type": "System.Collections.Generic.IEnumerable\u00601[[Hoangnhhe171693.Models.Xa, Hoangnhhe171693, Version=1.0.0.0, Culture=neutral, PublicKeyToken=null]]",
        "MediaTypes": [
          "text/plain",
          "application/json",
          "text/json"
        ],
        "StatusCode": 200
      },
      {
        "Type": "System.String",
        "MediaTypes": [
          "text/plain",
          "application/json",
          "text/json"
        ],
        "StatusCode": 400
      }
    ]
  },
  {
    "ContainingType": "Hoangnhhe171693.Controllers.XaController",
    "Method": "SoftDeleteXaAsync",
    "RelativePath": "api/Xa/change-status/{id}",
    "HttpMethod": "PUT",
    "IsController": true,
    "Order": 0,
    "Parameters": [
      {
        "Name": "id",
        "Type": "System.Int32",
        "IsRequired": true
      },
      {
        "Name": "newStatus",
        "Type": "System.String",
        "IsRequired": false
      }
    ],
    "ReturnTypes": [
      {
        "Type": "System.Collections.Generic.IEnumerable\u00601[[Hoangnhhe171693.Models.Xa, Hoangnhhe171693, Version=1.0.0.0, Culture=neutral, PublicKeyToken=null]]",
        "MediaTypes": [
          "text/plain",
          "application/json",
          "text/json"
        ],
        "StatusCode": 200
      },
      {
        "Type": "System.String",
        "MediaTypes": [
          "text/plain",
          "application/json",
          "text/json"
        ],
        "StatusCode": 400
      }
    ]
  },
  {
    "ContainingType": "Hoangnhhe171693.Controllers.XaController",
    "Method": "HardDeleteXaAsync",
    "RelativePath": "api/Xa/delete-permanent/{id}",
    "HttpMethod": "DELETE",
    "IsController": true,
    "Order": 0,
    "Parameters": [
      {
        "Name": "id",
        "Type": "System.Int32",
        "IsRequired": true
      }
    ],
    "ReturnTypes": [
      {
        "Type": "System.Collections.Generic.IEnumerable\u00601[[Hoangnhhe171693.Models.Xa, Hoangnhhe171693, Version=1.0.0.0, Culture=neutral, PublicKeyToken=null]]",
        "MediaTypes": [
          "text/plain",
          "application/json",
          "text/json"
        ],
        "StatusCode": 200
      },
      {
        "Type": "System.String",
        "MediaTypes": [
          "text/plain",
          "application/json",
          "text/json"
        ],
        "StatusCode": 400
      }
    ]
  },
  {
    "ContainingType": "Hoangnhhe171693.Controllers.XaController",
    "Method": "FindByNameAsync",
    "RelativePath": "api/Xa/find-by-name/{name}",
    "HttpMethod": "GET",
    "IsController": true,
    "Order": 0,
    "Parameters": [
      {
        "Name": "name",
        "Type": "System.String",
        "IsRequired": true
      }
    ],
    "ReturnTypes": [
      {
        "Type": "System.Collections.Generic.IEnumerable\u00601[[Hoangnhhe171693.Models.Xa, Hoangnhhe171693, Version=1.0.0.0, Culture=neutral, PublicKeyToken=null]]",
        "MediaTypes": [
          "text/plain",
          "application/json",
          "text/json"
        ],
        "StatusCode": 200
      },
      {
        "Type": "System.String",
        "MediaTypes": [
          "text/plain",
          "application/json",
          "text/json"
        ],
        "StatusCode": 400
      }
    ]
  },
  {
    "ContainingType": "Hoangnhhe171693.Controllers.XaController",
    "Method": "FindByIdAsync",
    "RelativePath": "api/Xa/find-Id/{postalCode}",
    "HttpMethod": "GET",
    "IsController": true,
    "Order": 0,
    "Parameters": [
      {
        "Name": "postalCode",
        "Type": "System.Int32",
        "IsRequired": true
      }
    ],
    "ReturnTypes": [
      {
        "Type": "System.Collections.Generic.IEnumerable\u00601[[Hoangnhhe171693.Models.Xa, Hoangnhhe171693, Version=1.0.0.0, Culture=neutral, PublicKeyToken=null]]",
        "MediaTypes": [
          "text/plain",
          "application/json",
          "text/json"
        ],
        "StatusCode": 200
      },
      {
        "Type": "System.String",
        "MediaTypes": [
          "text/plain",
          "application/json",
          "text/json"
        ],
        "StatusCode": 400
      }
    ]
  },
  {
    "ContainingType": "Hoangnhhe171693.Controllers.XaController",
    "Method": "GetAllXaAsync",
    "RelativePath": "api/Xa/get-all",
    "HttpMethod": "GET",
    "IsController": true,
    "Order": 0,
    "Parameters": [],
    "ReturnTypes": [
      {
        "Type": "System.Collections.Generic.IEnumerable\u00601[[Hoangnhhe171693.Models.Xa, Hoangnhhe171693, Version=1.0.0.0, Culture=neutral, PublicKeyToken=null]]",
        "MediaTypes": [
          "text/plain",
          "application/json",
          "text/json"
        ],
        "StatusCode": 200
      },
      {
        "Type": "System.String",
        "MediaTypes": [
          "text/plain",
          "application/json",
          "text/json"
        ],
        "StatusCode": 400
      }
    ]
  },
  {
    "ContainingType": "Hoangnhhe171693.Controllers.XaController",
    "Method": "getXaByIdHuyen",
    "RelativePath": "api/Xa/huyen/{id}",
    "HttpMethod": "GET",
    "IsController": true,
    "Order": 0,
    "Parameters": [
      {
        "Name": "id",
        "Type": "System.Int32",
        "IsRequired": true
      }
    ],
    "ReturnTypes": [
      {
        "Type": "System.Collections.Generic.IEnumerable\u00601[[Hoangnhhe171693.Models.Xa, Hoangnhhe171693, Version=1.0.0.0, Culture=neutral, PublicKeyToken=null]]",
        "MediaTypes": [
          "text/plain",
          "application/json",
          "text/json"
        ],
        "StatusCode": 200
      },
      {
        "Type": "System.String",
        "MediaTypes": [
          "text/plain",
          "application/json",
          "text/json"
        ],
        "StatusCode": 400
      }
    ]
  },
  {
    "ContainingType": "Hoangnhhe171693.Controllers.XaController",
    "Method": "UpdateXaAsync",
    "RelativePath": "api/Xa/update/{id}",
    "HttpMethod": "PUT",
    "IsController": true,
    "Order": 0,
    "Parameters": [
      {
        "Name": "update",
        "Type": "Hoangnhhe171693.Models.DTO.Request.Xa.XaUpdate",
        "IsRequired": true
      },
      {
        "Name": "id",
        "Type": "System.Int32",
        "IsRequired": true
      }
    ],
    "ReturnTypes": [
      {
        "Type": "System.Collections.Generic.IEnumerable\u00601[[Hoangnhhe171693.Models.Xa, Hoangnhhe171693, Version=1.0.0.0, Culture=neutral, PublicKeyToken=null]]",
        "MediaTypes": [
          "text/plain",
          "application/json",
          "text/json"
        ],
        "StatusCode": 200
      },
      {
        "Type": "System.String",
        "MediaTypes": [
          "text/plain",
          "application/json",
          "text/json"
        ],
        "StatusCode": 400
      }
    ]
  }
]